instec/MK2000.py
instec/MK2000B.py
instec/MK2000VCP.py
instec/__init__.py
instec/command.py
instec/constants.py
instec/controller.py
instec/pid.py
instec/profile.py
instec/temperature.py
instec-1.2.0.dist-info/METADATA
instec-1.2.0.dist-info/WHEEL
instec-1.2.0.dist-info/licenses/LICENSE.txt
instec-1.2.0.dist-info/RECORD
