Metadata-Version: 2.4
Name: instec
Version: 1.2.0
Summary: A basic implementation of SCPI commands for the MK2000B in Python.
Project-URL: Homepage, https://github.com/instecinc/pyinstec
Project-URL: Issues, https://github.com/instecinc/pyinstec/issues
Author-email: Matthew Chen <matthew.chen@instec.com>
License: MIT License
License-File: LICENSE.txt
Classifier: License :: OSI Approved :: MIT License
Classifier: Operating System :: OS Independent
Classifier: Programming Language :: Python :: 3
Requires-Python: >=3.10
Requires-Dist: pyserial>=3.0
